{
   "funds":[
      {
         "id":"1",
         "name":"Рубли",
         "image":"rublesign.circle.fill",
         "balance":"999"
      },
      {
         "id":"2",
         "name":"Доллары",
         "image":"dollarsign.circle.fill",
         "balance":"888"
      },
      {
         "id":"3",
         "name":"Евро",
         "image":"eurosign.circle.fill",
         "balance":"777"
      },
      {
         "id":"4",
         "name":"Наличка",
         "image":"banknote.fill",
         "balance":"0,15"
      }

   ],
   "expenses":[
      {
         "id":"1",
         "name":"Продукты",
         "image":"carrot.fill",
         "amount":"123",
         "plan":"10"
      },
      {
         "id":"2",
         "name":"Еда вне дома",
         "image":"fork.knife",
         "amount":"321",
         "plan":"15"
      },
      {
         "id":"3",
         "name":"Кофе",
         "image":"cup.and.saucer.fill",
         "amount":"99",
         "plan":"20"
      },
      {
         "id":"4",
         "name":"Спорт",
         "image":"figure.highintensity.intervaltraining",
         "amount":"0",
         "plan":""
      },
      {
         "id":"5",
         "name":"Разное",
         "image":"circle.grid.3x3.fill",
         "amount":"333",
         "plan":"25"
      },
      {
         "id":"6",
         "name":"Развлечения",
         "image":"gamecontroller.fill",
         "amount":"999",
         "plan":"30"
      }
   ]
}
